sc2replaystats_uploader/__init__.py
sc2replaystats_uploader/cli.py
sc2replaystats_uploader/sc2replaystats_uploader.py
sc2replaystats_uploader-0.2.6.dist-info/AUTHORS.rst
sc2replaystats_uploader-0.2.6.dist-info/LICENSE
sc2replaystats_uploader-0.2.6.dist-info/METADATA
sc2replaystats_uploader-0.2.6.dist-info/WHEEL
sc2replaystats_uploader-0.2.6.dist-info/entry_points.txt
sc2replaystats_uploader-0.2.6.dist-info/top_level.txt
sc2replaystats_uploader-0.2.6.dist-info/RECORD
