Metadata-Version: 2.1
Name: sc2replaystats-uploader
Version: 0.2.6
Summary: Script to automatically upload new files appearing in a directory to sc2replaystats.
Home-page: https://github.com/stanczakdominik/sc2replaystats_uploader
Author: Dominik Stańczak
Author-email: stanczakdominik@gmail.com
License: MIT license
Keywords: sc2replaystats_uploader
Platform: UNKNOWN
Classifier: Development Status :: 2 - Pre-Alpha
Classifier: Intended Audience :: Developers
Classifier: License :: OSI Approved :: MIT License
Classifier: Natural Language :: English
Classifier: Programming Language :: Python :: 3
Classifier: Programming Language :: Python :: 3.6
Classifier: Programming Language :: Python :: 3.7
Classifier: Programming Language :: Python :: 3.8
Requires-Python: >=3.6
Requires-Dist: Click (>=7.0)
Requires-Dist: requests
Requires-Dist: watchdog
Requires-Dist: setuptools
